c7n/__init__.py
c7n/cache.py
c7n/cli.py
c7n/commands.py
c7n/config.py
c7n/credentials.py
c7n/ctx.py
c7n/cwe.py
c7n/data.py
c7n/deprecated.py
c7n/element.py
c7n/exceptions.py
c7n/executor.py
c7n/handler.py
c7n/loader.py
c7n/log.py
c7n/lookup.py
c7n/manager.py
c7n/mu.py
c7n/output.py
c7n/policy.py
c7n/provider.py
c7n/query.py
c7n/registry.py
c7n/resolver.py
c7n/schema.py
c7n/sqsexec.py
c7n/structure.py
c7n/tags.py
c7n/testing.py
c7n/utils.py
c7n/varfmt.py
c7n/version.py
c7n/actions/__init__.py
c7n/actions/autoscaling.py
c7n/actions/autotag.py
c7n/actions/core.py
c7n/actions/invoke.py
c7n/actions/metric.py
c7n/actions/network.py
c7n/actions/notify.py
c7n/actions/policy.py
c7n/actions/webhook.py
c7n/filters/__init__.py
c7n/filters/backup.py
c7n/filters/config.py
c7n/filters/core.py
c7n/filters/costhub.py
c7n/filters/health.py
c7n/filters/iamaccess.py
c7n/filters/iamanalyzer.py
c7n/filters/kms.py
c7n/filters/metrics.py
c7n/filters/missing.py
c7n/filters/multiattr.py
c7n/filters/offhours.py
c7n/filters/policystatement.py
c7n/filters/related.py
c7n/filters/revisions.py
c7n/filters/vpc.py
c7n/filters/waf.py
c7n/reports/__init__.py
c7n/reports/csvout.py
c7n/resources/__init__.py
c7n/resources/accessanalyzer.py
c7n/resources/account.py
c7n/resources/acm.py
c7n/resources/airflow.py
c7n/resources/ami.py
c7n/resources/apigw.py
c7n/resources/appelb.py
c7n/resources/appflow.py
c7n/resources/appmesh.py
c7n/resources/appstream.py
c7n/resources/appsync.py
c7n/resources/artifact.py
c7n/resources/asg.py
c7n/resources/athena.py
c7n/resources/aws.py
c7n/resources/awslambda.py
c7n/resources/backup.py
c7n/resources/batch.py
c7n/resources/bedrock.py
c7n/resources/budgets.py
c7n/resources/cfn.py
c7n/resources/cloudfront.py
c7n/resources/cloudsearch.py
c7n/resources/cloudtrail.py
c7n/resources/code.py
c7n/resources/cognito.py
c7n/resources/comprehend.py
c7n/resources/config.py
c7n/resources/connect.py
c7n/resources/cw.py
c7n/resources/datapipeline.py
c7n/resources/datasync.py
c7n-0.9.49.dist-info/METADATA
c7n-0.9.49.dist-info/WHEEL
c7n-0.9.49.dist-info/entry_points.txt
c7n-0.9.49.dist-info/licenses/LICENSE
c7n-0.9.49.dist-info/RECORD
