Metadata-Version: 2.4
Name: c7n
Version: 0.9.49
Summary: Cloud Custodian - Policy Rules Engine
Project-URL: Bug Tracker, https://github.com/cloud-custodian/cloud-custodian/issues
Project-URL: homepage, https://cloudcustodian.io
Project-URL: repository, https://github.com/cloud-custodian/cloud-custodian
Project-URL: documentation, https://cloudcustodian.io/docs
Author: Cloud Custodian Project
License-Expression: Apache-2.0
License-File: LICENSE
Classifier: License :: OSI Approved :: Apache Software License
Classifier: Topic :: System :: Distributed Computing
Classifier: Topic :: System :: Systems Administration
Requires-Python: <4.0.0,>=3.10.2
Requires-Dist: argcomplete ==3.6.3
Requires-Dist: boto3 ==1.42.27
Requires-Dist: cryptography ==45.0.7
Requires-Dist: jsonschema ==4.26.0
Requires-Dist: python-dateutil ==2.9.0.post0
Requires-Dist: pyyaml ==6.0.3
Requires-Dist: tabulate ==0.9.0
Requires-Dist: urllib3 ==2.6.3
